awslabs/__init__.py
awslabs/cost_explorer_mcp_server/__init__.py
awslabs/cost_explorer_mcp_server/helpers.py
awslabs/cost_explorer_mcp_server/server.py
awslabs_cost_explorer_mcp_server-1.0.0.dist-info/METADATA
awslabs_cost_explorer_mcp_server-1.0.0.dist-info/WHEEL
awslabs_cost_explorer_mcp_server-1.0.0.dist-info/entry_points.txt
awslabs_cost_explorer_mcp_server-1.0.0.dist-info/licenses/LICENSE
awslabs_cost_explorer_mcp_server-1.0.0.dist-info/licenses/NOTICE
awslabs_cost_explorer_mcp_server-1.0.0.dist-info/RECORD
