Metadata-Version: 2.4
Name: awslabs.cost-explorer-mcp-server
Version: 1.0.0
Summary: MCP server for analyzing AWS costs and usage data through the AWS Cost Explorer API
Project-URL: Homepage, https://awslabs.github.io/mcp/
Project-URL: Documentation, https://awslabs.github.io/mcp/servers/cost-explorer-mcp-server/
Project-URL: Source, https://github.com/awslabs/mcp.git
Project-URL: Bug Tracker, https://github.com/awslabs/mcp/issues
Project-URL: Changelog, https://github.com/awslabs/mcp/blob/main/src/cost-explorer-mcp-server/CHANGELOG.md
Author: Amazon Web Services
Author-email: AWSLabs MCP <203918161+awslabs-mcp@users.noreply.github.com>
License: Apache-2.0
License-File: LICENSE
License-File: NOTICE
Classifier: License :: OSI Approved :: Apache Software License
Classifier: Operating System :: OS Independent
Classifier: Programming Language :: Python
Classifier: Programming Language :: Python :: 3
Classifier: Programming Language :: Python :: 3.10
Classifier: Programming Language :: Python :: 3.11
Classifier: Programming Language :: Python :: 3.12
Classifier: Programming Language :: Python :: 3.13
Requires-Python: >=3.10
Requires-Dist: boto3>=1.36.20
Requires-Dist: fastmcp>=0.1.0
Requires-Dist: pandas>=2.2.3
Requires-Dist: pydantic>=2.10.6
